{
    "133": {
        "positive": [
            "-60% ontploffingschade van raketsprongen"
        ], 
        "type": "Laarzen", 
        "description": "Gunboats"
    }, 
    "132": {
        "alt": [
            "Dit wapen heeft een groot slagbereik.\r\nZorgt voor een hogere snelheid en gezondheid bij elk leven dat je neemt."
        ], 
        "type": "Zwaard", 
        "negative": [
            "-25 maximale gezondheid voor drager", 
            "Geen willekeurige voltreffers"
        ], 
        "description": "Eyelander"
    }, 
    "131": {
        "positive": [
            "+50% bestendigheid tegen vuurschade voor de drager", 
            "+40% bestendigheid tegen explosieschade voor de drager"
        ], 
        "alt": [
            "Alt-Fire: verhoogt de aanvalskracht door je vijanden van voren aan te vallen."
        ], 
        "type": "Schild", 
        "description": "Chargin' Targe"
    }, 
    "130": {
        "positive": [
            "+50% max. secundaire munitie voor de drager", 
            "+6 max. pijpbommen", 
            "Laat kleefbommen vlak bij het richtmerk ontploffen", 
            "Kan kleefbommen van de vijand vernietigen"
        ], 
        "type": "Kleefbommenwerper", 
        "negative": [
            "0.4 sec langere bombewapeningstijd"
        ], 
        "description": "Scottish Resistance"
    }, 
    "137": {
        "type": "Hat", 
        "description": "Aardig stapeltje hoeden"
    }, 
    "136": {
        "alt": [
            "Tweede plaats propagandawedstrijd"
        ], 
        "type": "Hat", 
        "description": "Amber's Rad As All Hell Hat"
    }, 
    "135": {
        "type": "Hat", 
        "description": "Hoedentoren"
    }, 
    "134": {
        "alt": [
            "Eerste plaats propagandawedstrijd"
        ], 
        "type": "Hat", 
        "description": "J.Axer's Dapper Topper"
    }, 
    "139": {
        "type": "Hat", 
        "description": "Bescheiden stapeltje hoeden"
    }, 
    "138": {
        "alt": [
            "Derde plaats propagandawedstrijd"
        ], 
        "type": "Hat", 
        "description": "Uncle Sam"
    }, 
    "24": {
        "type": "Revolver", 
        "description": "Revolver"
    }, 
    "25": {
        "type": "PDA", 
        "description": "PDA"
    }, 
    "26": {
        "type": "PDA", 
        "description": "PDA"
    }, 
    "27": {
        "type": "PDA", 
        "description": "PDA"
    }, 
    "20": {
        "type": "Kleefbommenwerper", 
        "description": "Kleefbommenwerper"
    }, 
    "21": {
        "type": "Vlammenwerper", 
        "description": "Vlammenwerper"
    }, 
    "22": {
        "type": "Pistool", 
        "description": "Pistool"
    }, 
    "23": {
        "type": "Pistool", 
        "description": "Pistool"
    }, 
    "95": {
        "type": "Hat", 
        "description": "Engineerspet"
    }, 
    "28": {
        "type": "PDA", 
        "description": "PDA"
    }, 
    "29": {
        "type": "Medigun", 
        "description": "Medigun"
    }, 
    "94": {
        "type": "Hat", 
        "description": "Cowboyhoed"
    }, 
    "0": {
        "type": "Knuppel", 
        "description": "Knuppel"
    }, 
    "4": {
        "type": "Mes", 
        "description": "Mes"
    }, 
    "8": {
        "type": "Bottenzaag", 
        "description": "Bottenzaag"
    }, 
    "96": {
        "type": "Hat", 
        "description": "Russische officiersmuts"
    }, 
    "120": {
        "type": "Hat", 
        "description": "Hoge hoed"
    }, 
    "121": {
        "type": "Medaille", 
        "description": "Medaille voor bewezen diensten"
    }, 
    "122": {
        "type": "Cheat Detector", 
        "description": "Er is gesignaleerd dat met jouw account het distributiesysteem voor items is omzeild. We hebben de items die illegaal zijn verkregen, verwijderd.\r\n\r\nBij verdere overtredingen verlies je al je items."
    }, 
    "123": {
        "type": "Cheat Detector", 
        "description": "Er is gesignaleerd dat met jouw account het distributiesysteem voor items is omzeild. We hebben alle items uit je voorraad verwijderd.\r\n\r\nBij verdere overtredingen wordt je account mogelijk geblokkeerd."
    }, 
    "124": {
        "type": "Cheat Detector", 
        "description": "Gefeliciteerd! Jouw eerlijkheid is beloond met een nieuw hoofddeksel!\r\n\r\n(Een aantal andere spelers was minder gewetensvol en minder fortuinlijk)"
    }, 
    "125": {
        "alt": [
            "Toegebrachte schade %s1%"
        ], 
        "type": "Integriteitsaureool", 
        "description": "Aureool"
    }, 
    "126": {
        "type": "Veteranenbaret", 
        "description": "Bill's pet"
    }, 
    "127": {
        "positive": [
            "Mini-crits bij luchtdoelen", 
            "Toegebrachte schade +25%", 
            "+80% projectielsnelheid"
        ], 
        "type": "Raketwerper", 
        "negative": [
            "-70% explosiebereik"
        ], 
        "description": "Direct Hit"
    }, 
    "128": {
        "positive": [
            "Schade en bewegingssnelheid nemen toe naarmate wanneer de gebruiker gewond raakt"
        ], 
        "type": "Pikhouweel", 
        "description": "Equalizer"
    }, 
    "129": {
        "type": "Strijdvaandel", 
        "description": "Buff Banner"
    }, 
    "59": {
        "positive": [
            "+80% herstelsnelheid vermomming"
        ], 
        "alt": [
            "Soort vermomming: dood houden"
        ], 
        "type": "Onzichtbaarheidshorloge", 
        "negative": [
            "+60% vervalsnelheid vermomming"
        ], 
        "description": "Dead Ringer"
    }, 
    "58": {
        "alt": [
            "Uitgeruste vijanden krijgen mini-crits\r\nOok handig om vuur te doven"
        ], 
        "type": "Jarate", 
        "description": "Jarate"
    }, 
    "55": {
        "type": "Hat", 
        "description": "Gleufhoed"
    }, 
    "54": {
        "type": "Hat", 
        "description": "Voorraad soldaat"
    }, 
    "57": {
        "positive": [
            "Blokkeert \u00e9\u00e9n ruggesteek"
        ], 
        "type": "Schild", 
        "description": "Razorback"
    }, 
    "56": {
        "type": "Boog", 
        "description": "Huntsman"
    }, 
    "51": {
        "type": "Hat", 
        "description": "Pyro's petje"
    }, 
    "50": {
        "type": "Hat", 
        "description": "Pruisische helm"
    }, 
    "53": {
        "type": "Hat", 
        "description": "Trofee\u00ebnriem"
    }, 
    "52": {
        "type": "Hat", 
        "description": "Slagmanhelm"
    }, 
    "5010": {
        "alt": [
            "Wordt gebruikt om een klasse van blauwdrukken te specificeren"
        ], 
        "type": "Item ontwerpen", 
        "description": "Klasseteken - Spy"
    }, 
    "5011": {
        "alt": [
            "Wordt gebruikt om een klasse van blauwdrukken te specificeren"
        ], 
        "type": "Item ontwerpen", 
        "description": "Klasseteken - Engineer"
    }, 
    "5012": {
        "alt": [
            "Wordt gebruikt om een uitrustingspositie van blauwdrukken te specificeren"
        ], 
        "type": "Item ontwerpen", 
        "description": "Positieteken - Primair"
    }, 
    "5013": {
        "alt": [
            "Wordt gebruikt om een uitrustingspositie van blauwdrukken te specificeren"
        ], 
        "type": "Item ontwerpen", 
        "description": "Positieteken - Secundair"
    }, 
    "5014": {
        "alt": [
            "Wordt gebruikt om een uitrustingspositie van blauwdrukken te specificeren"
        ], 
        "type": "Item ontwerpen", 
        "description": "Positieteken - Slagwapen"
    }, 
    "5015": {
        "alt": [
            "Wordt gebruikt om een uitrustingspositie van blauwdrukken te specificeren"
        ], 
        "type": "Item ontwerpen", 
        "description": "Positieteken - Granaat"
    }, 
    "5016": {
        "alt": [
            "Wordt gebruikt om een uitrustingspositie van blauwdrukken te specificeren"
        ], 
        "type": "Item ontwerpen", 
        "description": "Positieteken - Gebouw"
    }, 
    "5017": {
        "alt": [
            "Wordt gebruikt om een uitrustingspositie van blauwdrukken te specificeren"
        ], 
        "type": "Item ontwerpen", 
        "description": "Positieteken - PDA"
    }, 
    "5018": {
        "alt": [
            "Wordt gebruikt om een uitrustingspositie van blauwdrukken te specificeren"
        ], 
        "type": "Item ontwerpen", 
        "description": "Positieteken - PDA2"
    }, 
    "5019": {
        "alt": [
            "Wordt gebruikt om een uitrustingspositie van blauwdrukken te specificeren"
        ], 
        "type": "Item ontwerpen", 
        "description": "Positieteken - Hoofd"
    }, 
    "115": {
        "type": "Feestdaghoed", 
        "description": "Licht verontrustende papieren zak"
    }, 
    "117": {
        "type": "Hat", 
        "description": "Coole coupe"
    }, 
    "116": {
        "alt": [
            "Met geborduurde initialen 'Z.M.'"
        ], 
        "type": "Hat", 
        "description": "Gruwelijke gibus"
    }, 
    "111": {
        "type": "Hat", 
        "description": "Glimmende gelcoupe"
    }, 
    "110": {
        "type": "Hat", 
        "description": "Gele hoofdband"
    }, 
    "118": {
        "type": "Hat", 
        "description": "Kale knar"
    }, 
    "3": {
        "type": "Kukri-mes", 
        "description": "Kukri-mes"
    }, 
    "7": {
        "type": "Moersleutel", 
        "description": "Moersleutel"
    }, 
    "5003": {
        "alt": [
            "Wordt gebruikt om een klasse van blauwdrukken te specificeren"
        ], 
        "type": "Item ontwerpen", 
        "description": "Klasseteken - Scout"
    }, 
    "5002": {
        "type": "Item ontwerpen", 
        "description": "Bewerkt metaal"
    }, 
    "5001": {
        "type": "Item ontwerpen", 
        "description": "Gerecycled metaal"
    }, 
    "5000": {
        "type": "Item ontwerpen", 
        "description": "Schroot"
    }, 
    "5007": {
        "alt": [
            "Wordt gebruikt om een klasse van blauwdrukken te specificeren"
        ], 
        "type": "Item ontwerpen", 
        "description": "Klasseteken - Heavy"
    }, 
    "5006": {
        "alt": [
            "Wordt gebruikt om een klasse van blauwdrukken te specificeren"
        ], 
        "type": "Item ontwerpen", 
        "description": "Klasseteken - Demoman"
    }, 
    "5005": {
        "alt": [
            "Wordt gebruikt om een klasse van blauwdrukken te specificeren"
        ], 
        "type": "Item ontwerpen", 
        "description": "Klasseteken - Soldier"
    }, 
    "5004": {
        "alt": [
            "Wordt gebruikt om een klasse van blauwdrukken te specificeren"
        ], 
        "type": "Item ontwerpen", 
        "description": "Klasseteken - Sniper"
    }, 
    "5009": {
        "alt": [
            "Wordt gebruikt om een klasse van blauwdrukken te specificeren"
        ], 
        "type": "Item ontwerpen", 
        "description": "Klasseteken - Pyro"
    }, 
    "5008": {
        "alt": [
            "Wordt gebruikt om een klasse van blauwdrukken te specificeren"
        ], 
        "type": "Item ontwerpen", 
        "description": "Klasseteken - Medic"
    }, 
    "108": {
        "type": "Hat", 
        "description": "Bolhoed"
    }, 
    "109": {
        "type": "Hat", 
        "description": "Rieten hoed"
    }, 
    "102": {
        "type": "Hat", 
        "description": "Hanekammuts"
    }, 
    "103": {
        "type": "Hat", 
        "description": "Camerabaard"
    }, 
    "100": {
        "type": "Hat", 
        "description": "Schotse muts"
    }, 
    "101": {
        "type": "Hat", 
        "description": "Tirolerhoed"
    }, 
    "106": {
        "type": "Hat", 
        "description": "Bonk-helm"
    }, 
    "107": {
        "type": "Hat", 
        "description": "Schavuitenpet"
    }, 
    "104": {
        "type": "Hat", 
        "description": "Doktersspiegel"
    }, 
    "105": {
        "type": "Hat", 
        "description": "Korpshelm"
    }, 
    "39": {
        "type": "Lichtpistool", 
        "description": "Flare Gun"
    }, 
    "38": {
        "positive": [
            "100% voltreffer vs. brandende spelers"
        ], 
        "type": "Vuurbijl", 
        "negative": [
            "Geen voltreffers vs. niet-brandende spelers", 
            "-50% schade vs. niet-brandende spelers"
        ], 
        "description": "Axtinguisher"
    }, 
    "33": {
        "type": "Injectiepistool", 
        "description": "Injectiepistool"
    }, 
    "32": {
        "type": "Bottenzaag", 
        "description": "Bottenzaag"
    }, 
    "31": {
        "type": "Lichtpistool", 
        "description": "Lichtpistool"
    }, 
    "30": {
        "type": "Onzichtbaarheidshorloge", 
        "description": "Onzichtbaarheidshorloge"
    }, 
    "37": {
        "positive": [
            "Bij treffer: 25% \u00fcberlading toegevoegd"
        ], 
        "type": "Bottenzaag", 
        "negative": [
            "Vuursnelheid -20% lager"
        ], 
        "description": "Ubersaw"
    }, 
    "36": {
        "positive": [
            "Bij treffer: +3 gezondheid"
        ], 
        "type": "Injectiepistool", 
        "negative": [
            "De gezondheid van de drager gaat met -2 per seconde achteruit"
        ], 
        "description": "Blutsauger"
    }, 
    "35": {
        "positive": [
            "Laadsnelheid \u00fcberlading+25%"
        ], 
        "alt": [
            "\u00dcberlading geeft 100% kans op voltreffer"
        ], 
        "type": "Medigun", 
        "description": "Kritzkrieg"
    }, 
    "34": {
        "type": "Medigun", 
        "description": "Medigun"
    }, 
    "60": {
        "positive": [
            "+100% herstelsnelheid vermomming"
        ], 
        "alt": [
            "Soort vermomming: bewegingsgevoelig"
        ], 
        "type": "Onzichtbaarheidshorloge", 
        "description": "Cloak and Dagger"
    }, 
    "61": {
        "positive": [
            "Voltreffers bij nauwkeurig hoofdschot"
        ], 
        "type": "Revolver", 
        "negative": [
            "Toegebrachte schade -15%", 
            "Vuursnelheid -20% lager"
        ], 
        "description": "Ambassador"
    }, 
    "97": {
        "type": "Hat", 
        "description": "Altomuts"
    }, 
    "179": {
        "type": "Hat", 
        "description": "Tricorne"
    }, 
    "178": {
        "type": "Hat", 
        "description": "Gehoorbeschermers"
    }, 
    "177": {
        "alt": [
            "Niets"
        ], 
        "type": "Hat", 
        "description": "Die Kaikers"
    }, 
    "175": {
        "type": "Hat", 
        "description": "Besnorde Heer"
    }, 
    "174": {
        "type": "Hat", 
        "description": "Kroontjespet"
    }, 
    "172": {
        "positive": [
            "Toegebrachte schade +20%"
        ], 
        "type": "Bijl", 
        "negative": [
            "15% lagere bewegingssnelheid bij drager"
        ], 
        "description": "TF_Unique_BattleAxe"
    }, 
    "171": {
        "positive": [
            "Bij treffer: 6 seconden bloeden"
        ], 
        "type": "Kukri-mes", 
        "negative": [
            "Toegebrachte schade -50%"
        ], 
        "description": "TF_Unique_TribalmanKukri"
    }, 
    "170": {
        "alt": [
            "Huurdatum: %s1"
        ], 
        "type": "Insigne", 
        "description": "Oerkrijger"
    }, 
    "182": {
        "type": "Hat", 
        "description": "Brandweerhelm"
    }, 
    "183": {
        "type": "Hat", 
        "description": "Drilmeestershoed"
    }, 
    "180": {
        "type": "Hat", 
        "description": "Franse Baret"
    }, 
    "181": {
        "type": "Hat", 
        "description": "Vishoedje"
    }, 
    "184": {
        "type": "Hat", 
        "description": "Gatsby-pet"
    }, 
    "6": {
        "type": "Spade", 
        "description": "Spade"
    }, 
    "185": {
        "type": "Hat", 
        "description": "Bandana"
    }, 
    "99": {
        "type": "Hat", 
        "description": "Vikinghelm"
    }, 
    "98": {
        "type": "Hat", 
        "description": "Kookpan"
    }, 
    "169": {
        "type": "Moersleutel", 
        "description": "TF_Unique_Golden_Wrench"
    }, 
    "164": {
        "alt": [
            "Huurdatum: %s1"
        ], 
        "type": "Insigne", 
        "description": "Doorwinterde Veteraan"
    }, 
    "165": {
        "alt": [
            "Huurdatum: %s1"
        ], 
        "type": "Insigne", 
        "description": "Fortuinlijke Soldaat"
    }, 
    "166": {
        "alt": [
            "Huurdatum: %s1"
        ], 
        "type": "Insigne", 
        "description": "Huurling"
    }, 
    "160": {
        "alt": [
            "De ultieme semi-verborgen wapens.\r\nNatuurlijk heb je dit wapen nodig,\r\nmaar waar berg je het op?"
        ], 
        "type": "Pistool", 
        "description": "Lugermorph"
    }, 
    "161": {
        "alt": [
            "Combineert stijl met stopkracht.\r\nVroeger exclusief voorbehouden aan politieagenten,\r\nmaar nu ook beschikbaar voor bloeddorstige moordenaars."
        ], 
        "type": "Revolver", 
        "description": "Big Kill"
    }, 
    "162": {
        "alt": [
            "Traditionele hoofddeksels, vervaardigd door vredelievende boeren\r\nuit de Filipijnen. De uitgeholde schedel\r\nneemt het zweet op in het heetst van de strijd."
        ], 
        "type": "Hat", 
        "description": "Max' halve hoofd"
    }, 
    "163": {
        "alt": [
            "Onder invloed hiervan zijn toegebrachte\r\nen opgelopen schade mini-crits", 
            "Voegt 30 seconden lang +50 maximale gezondheid toe"
        ], 
        "type": "Lunchtrommel", 
        "description": "TF_Unique_EnergyDrink_CritCola"
    }, 
    "11": {
        "type": "Shotgun", 
        "description": "Shotgun"
    }, 
    "10": {
        "type": "Shotgun", 
        "description": "Shotgun"
    }, 
    "13": {
        "type": "Scattergun", 
        "description": "Scattergun"
    }, 
    "12": {
        "type": "Shotgun", 
        "description": "Shotgun"
    }, 
    "15": {
        "type": "Minigun", 
        "description": "Minigun"
    }, 
    "14": {
        "type": "Snipergeweer", 
        "description": "Snipergeweer"
    }, 
    "17": {
        "type": "Injectiepistool", 
        "description": "Injectiepistool"
    }, 
    "16": {
        "type": "SMG", 
        "description": "SMG"
    }, 
    "19": {
        "type": "Granaatwerper", 
        "description": "Granaatwerper"
    }, 
    "18": {
        "type": "Raketwerper", 
        "description": "Raketwerper"
    }, 
    "151": {
        "type": "Hat", 
        "description": "Triboniophorus Tyrannus"
    }, 
    "150": {
        "type": "Hat", 
        "description": "Beanie"
    }, 
    "153": {
        "positive": [
            "Schade verwijdert Sappers", 
            "100% schade aan bouwsels"
        ], 
        "type": "Moker", 
        "negative": [
            "-25% schade aan spelers"
        ], 
        "description": "Homewrecker"
    }, 
    "152": {
        "type": "Hat", 
        "description": "Kabutohelm"
    }, 
    "155": {
        "positive": [
            "Bij treffer: 5 seconden bloeden"
        ], 
        "type": "Moersleutel", 
        "negative": [
            "Geen willekeurige voltreffers", 
            "20% kwetsbaarheid voor vuurschade voor de drager"
        ], 
        "description": "TF_Unique_Combat_Wrench"
    }, 
    "154": {
        "positive": [
            "Veroveringssnelheid van +1 voor de drager"
        ], 
        "type": "Ge\u00efmproviseerde knuppel", 
        "negative": [
            "10% kwetsbaarheid voor kogelschade voor de drager"
        ], 
        "description": "Pain Train"
    }, 
    "159": {
        "positive": [
            "Voegt 30 seconden lang +50 maximale gezondheid toe"
        ], 
        "type": "Lunchtrommel", 
        "description": "Dalokohs Bar"
    }, 
    "158": {
        "type": "Hat", 
        "description": "Tropenhelm"
    }, 
    "48": {
        "type": "Hat", 
        "description": "Mijnlamp"
    }, 
    "49": {
        "type": "Hat", 
        "description": "Rugbyhelm"
    }, 
    "46": {
        "type": "Lunchtrommel", 
        "description": "Bonk! Atomic Punch"
    }, 
    "47": {
        "type": "Hat", 
        "description": "Demoman's Fro"
    }, 
    "44": {
        "positive": [
            "Met deze knuppel kun je een venijnig balletje meppen"
        ], 
        "type": "Knuppel", 
        "negative": [
            "-15 maximale gezondheid voor drager"
        ], 
        "description": "Sandman"
    }, 
    "45": {
        "positive": [
            "Knockback op het doel en de schutter", 
            "Vuursnelheid +50% hoger", 
            "+20% kogels per schot"
        ], 
        "type": "Scattergun", 
        "negative": [
            "Magazijngrootte -60%", 
            "Toegebrachte schade -10%"
        ], 
        "description": "Force-A-Nature"
    }, 
    "42": {
        "type": "Lunchtrommel", 
        "description": "Sandvich"
    }, 
    "43": {
        "positive": [
            "Bij eliminatie: 5 seconden 100% kans op een voltreffer"
        ], 
        "type": "Vuisten", 
        "negative": [
            "Vuursnelheid -20% lager"
        ], 
        "description": "Killing Gloves of Boxing"
    }, 
    "40": {
        "positive": [
            "100% voltreffers in de rug", 
            "Toegebrachte schade +14%"
        ], 
        "type": "Vlammenwerper", 
        "negative": [
            "Geen willekeurige voltreffers", 
            "Geen compressiestoot"
        ], 
        "description": "Backburner"
    }, 
    "41": {
        "positive": [
            "Bij treffer: 100% kans om je doelwit te vertragen"
        ], 
        "type": "Minigun", 
        "negative": [
            "Toegebrachte schade -25%"
        ], 
        "description": "Natascha"
    }, 
    "1": {
        "type": "Fles", 
        "description": "Fles"
    }, 
    "5": {
        "type": "Vuisten", 
        "description": "Vuisten"
    }, 
    "9": {
        "type": "Shotgun", 
        "description": "Shotgun"
    }, 
    "146": {
        "type": "Hat", 
        "description": "Pooierhoed"
    }, 
    "147": {
        "type": "Hat", 
        "description": "Rechterspruik"
    }, 
    "144": {
        "type": "Hat", 
        "description": "Operatiemasker"
    }, 
    "145": {
        "type": "Hat", 
        "description": "Elvispruik"
    }, 
    "142": {
        "positive": [
            "+25 maximale gezondheid voor drager"
        ], 
        "type": "TF_Weapon_Robot_Arm", 
        "negative": [
            "Geen willekeurige voltreffers"
        ], 
        "description": "TF_Unique_Robot_Arm"
    }, 
    "143": {
        "alt": [
            "Specifiek besturingssysteem!"
        ], 
        "type": "Hat", 
        "description": "Oordopjes"
    }, 
    "140": {
        "alt": [
            "TF_Wrangler_Desc"
        ], 
        "type": "TF_Weapon_Laser_Pointer", 
        "description": "TF_Unique_Achievement_Laser_Pointer"
    }, 
    "141": {
        "type": "Shotgun", 
        "negative": [
            "Geen willekeurige voltreffers", 
            "Magazijngrootte -50%"
        ], 
        "description": "TF_Unique_Sentry_Shotgun"
    }, 
    "148": {
        "type": "Hat", 
        "description": "Lasmasker"
    }, 
    "2": {
        "type": "Vuurbijl", 
        "description": "Vuurbijl"
    }
}
